pre_pip/__init__.py
pre_pip/cli.py
pre_pip/install.py
pre_pip/main.py
pre_pip/uninstall.py
pre_pip-0.1.3.dist-info/entry_points.txt
pre_pip-0.1.3.dist-info/METADATA
pre_pip-0.1.3.dist-info/WHEEL
pre_pip-0.1.3.dist-info/LICENSE
pre_pip-0.1.3.dist-info/RECORD
