Metadata-Version: 2.1
Name: pre-pip
Version: 0.1.3
Summary: Run some python before your pip commands.
Author: Ratul Maharaj
Author-email: ratulmaharaj@looped.co.za
Requires-Python: >=3.11,<4.0
Classifier: Programming Language :: Python :: 3
Classifier: Programming Language :: Python :: 3.11
Requires-Dist: click (>=8.1.3,<9.0.0)
Requires-Dist: rich (>=12.6.0,<13.0.0)
